pygmail2/__init__.py
pygmail2/Addr.py
pygmail2/Pygmail.py
pygmail2/sendMailScript.py
pygmail2-0.3.6.dist-info/DESCRIPTION.rst
pygmail2-0.3.6.dist-info/entry_points.txt
pygmail2-0.3.6.dist-info/METADATA
pygmail2-0.3.6.dist-info/metadata.json
pygmail2-0.3.6.dist-info/RECORD
pygmail2-0.3.6.dist-info/top_level.txt
pygmail2-0.3.6.dist-info/WHEEL
