Metadata-Version: 2.0
Name: pygmail2
Version: 0.3.6
Summary: Send mail from gmail using python
Home-page: https://github.com/kindlychung/pygmail
Author: Kaiyin Zhong
Author-email: kindlychung@gmail.com
License: UNKNOWN
Keywords: gmail,email
Platform: UNKNOWN
